langgraph/checkpoint/base/__init__.py
langgraph/checkpoint/base/id.py
langgraph/checkpoint/base/py.typed
langgraph/checkpoint/memory/__init__.py
langgraph/checkpoint/memory/py.typed
langgraph/checkpoint/serde/__init__.py
langgraph/checkpoint/serde/base.py
langgraph/checkpoint/serde/encrypted.py
langgraph/checkpoint/serde/jsonplus.py
langgraph/checkpoint/serde/py.typed
langgraph/checkpoint/serde/types.py
langgraph/store/base/__init__.py
langgraph/store/base/batch.py
langgraph/store/base/embed.py
langgraph/store/base/py.typed
langgraph/store/memory/__init__.py
langgraph/store/memory/py.typed
langgraph_checkpoint-2.0.22.dist-info/LICENSE
langgraph_checkpoint-2.0.22.dist-info/METADATA
langgraph_checkpoint-2.0.22.dist-info/WHEEL
langgraph_checkpoint-2.0.22.dist-info/RECORD
