Metadata-Version: 2.1
Name: langgraph-checkpoint
Version: 2.0.22
Summary: Library with base interfaces for LangGraph checkpoint savers.
Home-page: https://www.github.com/langchain-ai/langgraph
License: MIT
Requires-Python: >=3.9.0,<4.0.0
Classifier: License :: OSI Approved :: MIT License
Classifier: Programming Language :: Python :: 3
Classifier: Programming Language :: Python :: 3.9
Classifier: Programming Language :: Python :: 3.10
Classifier: Programming Language :: Python :: 3.11
Classifier: Programming Language :: Python :: 3.12
Requires-Dist: langchain-core (>=0.2.38,<0.4)
Requires-Dist: ormsgpack (>=1.8.0,<2.0.0)
Project-URL: Repository, https://www.github.com/langchain-ai/langgraph
